kywy/__init__.py
kywy/__main__.py
kywy/client/__init__.py
kywy/client/benchmark.py
kywy/client/chat.py
kywy/client/commands.py
kywy/client/computation_nodes.py
kywy/client/configuration.py
kywy/client/data.py
kywy/client/data_generator.py
kywy/client/data_loader.py
kywy/client/data_providers.py
kywy/client/date_utils.py
kywy/client/dsl.py
kywy/client/entities.py
kywy/client/errors.py
kywy/client/generator.py
kywy/client/kawa_client.py
kywy/client/kawa_decorators.py
kywy/client/kawa_types.py
kywy/client/layout_builder.py
kywy/client/other.py
kywy/client/reporting.py
kywy/client/workflow_bindings.py
kywy/client/application/__init__.py
kywy/client/application/app_agent.py
kywy/client/application/app_dataset.py
kywy/client/application/app_filter.py
kywy/client/application/app_metric.py
kywy/client/application/app_model.py
kywy/client/application/app_page.py
kywy/client/application/app_relationship.py
kywy/client/application/app_reporter.py
kywy/client/application/app_synchronizer.py
kywy/client/application/app_variable.py
kywy/client/application/app_widget.py
kywy/client/application/application_builder.py
kywy/client/application/application_building_utils.py
kywy/client/application/build_sample_application.py
kywy/client/application/build_sample_application_simple.py
kywy/client/application/build_sample_dashboard.py
kywy/client/application/build_sample_report.py
kywy/client/application/build_sample_research.py
kywy/client/application/report_blocks.py
kywy/client/application/report_builder.py
kywy/client/application/research_builder.py
kywy/client/application/chat/chat.py
kywy/client/application/chat/jupyter.py
kywy/client/application/chat/source_code_utils.py
kywy/client/application/chat/utils.py
kywy/client/workflow/__init__.py
kywy/client/workflow/utils.py
kywy/client/workflow/workflow_builder.py
kywy/client/workflow/workflow_properties.py
kywy/client/workflow/workflow_tasks.py
kywy/test/__init__.py
kywy/test/kawa_base_e2e_test.py
kywy/test/computation/__init__.py
kywy-0.34.10.dist-info/METADATA
kywy-0.34.10.dist-info/WHEEL
kywy-0.34.10.dist-info/top_level.txt
kywy-0.34.10.dist-info/RECORD
