Metadata-Version: 2.4
Name: kywy
Version: 0.34.10
Summary: Python client for Kawa - https://docs.kawa.ai
Author-email: Kawa Analytics <emmmanuel@kawa.ai>, Kawa Analytics <max@kawa.ai>
Maintainer-email: Kawa Analytics <max@kawa.ai>, Kawa Analytics <emmmanuel@kawa.ai>
Requires-Python: >=3.9
Requires-Dist: requests>=2.28
Requires-Dist: numpy>=1.25.0
Requires-Dist: pandas>=2.2.0
Requires-Dist: matplotlib>=3.8.0
Requires-Dist: psutil>=5.9.4
Requires-Dist: pyarrow>=16.1.0
Requires-Dist: tzlocal>=4.2
Requires-Dist: pycryptodome>=3.18.0
Requires-Dist: pyyaml>=6.0.1
Requires-Dist: type_enforced>=1.4.0
Requires-Dist: python-dotenv>=1.0.0
Requires-Dist: icecream>=2.1.3
Requires-Dist: python-slugify>=7.0.0
Requires-Dist: packaging>=24.1.0
Requires-Dist: pytz>=2024.1
Provides-Extra: kerberos
Requires-Dist: gssapi; extra == "kerberos"
Requires-Dist: requests-kerberos; extra == "kerberos"
